{
  "unpublishedPage": {
    "name": "User Dashboard",
    "slug": "user-dashboard",
    "layouts": [
      {
        "viewMode": false,
        "dsl": {
          "widgetName": "MainContainer",
          "backgroundColor": "none",
          "rightColumn": 912,
          "snapColumns": 64,
          "detachFromLayout": true,
          "widgetId": "0",
          "topRow": 0,
          "bottomRow": 2180,
          "containerStyle": "none",
          "snapRows": 63,
          "parentRowSpace": 1,
          "type": "CANVAS_WIDGET",
          "canExtend": true,
          "version": 80,
          "minHeight": 640,
          "parentColumnSpace": 1,
          "dynamicBindingPathList": [],
          "leftColumn": 0
        },
        "layoutOnLoadActions": [
          [
            {
              "id": "User Dashboard_users_macids",
              "name": "users_macids",
              "confirmBeforeExecute": false,
              "pluginType": "DB",
              "jsonPathKeys": [],
              "timeoutInMillisecond": 10000
            }
          ],
          [
            {
              "id": "User Dashboard_device_list",
              "name": "device_list",
              "confirmBeforeExecute": false,
              "pluginType": "DB",
              "jsonPathKeys": [],
              "timeoutInMillisecond": 10000
            },
            {
              "id": "User Dashboard_subs_list",
              "name": "subs_list",
              "confirmBeforeExecute": false,
              "pluginType": "DB",
              "jsonPathKeys": [],
              "timeoutInMillisecond": 10000
            },
            {
              "id": "User Dashboard_users_list",
              "name": "users_list",
              "confirmBeforeExecute": false,
              "pluginType": "DB",
              "jsonPathKeys": [],
              "timeoutInMillisecond": 10000
            }
          ]
        ],
        "layoutOnLoadActionErrors": [],
        "validOnPageLoadActions": true,
        "id": "User Dashboard",
        "deleted": false,
        "policies": [],
        "userPermissions": []
      }
    ],
    "userPermissions": [],
    "policies": [],
    "isHidden": false
  },
  "deleted": false,
  "gitSyncId": "60cd8f14165e2a21a2661090_625aac200d3d384069c175c2"
}