{
  "accentColor": "{{appsmith.theme.colors.primaryColor}}",
  "animateLoading": true,
  "autoFocus": false,
  "borderRadius": "0px",
  "bottomRow": 12,
  "boxShadow": "none",
  "defaultText": "",
  "displayName": "Input",
  "dynamicBindingPathList": [
    {
      "key": "accentColor"
    }
  ],
  "dynamicHeight": "FIXED",
  "dynamicTriggerPathList": [],
  "hideCard": false,
  "iconAlign": "left",
  "iconSVG": "/static/media/icon.9f505595.svg",
  "inputType": "TEXT",
  "isDisabled": false,
  "isLoading": false,
  "isRequired": true,
  "isVisible": true,
  "key": "6z50yrmbbz",
  "label": "",
  "labelAlignment": "left",
  "labelPosition": "Left",
  "labelStyle": "",
  "labelTextSize": "0.875rem",
  "labelWidth": 5,
  "leftColumn": 23,
  "maxChars": "100",
  "maxDynamicHeight": 9000,
  "minDynamicHeight": 4,
  "parentColumnSpace": 12.58209228515625,
  "parentId": "j44tgpyjko",
  "parentRowSpace": 10,
  "placeholderText": "Coupon Code",
  "renderMode": "CANVAS",
  "resetOnSubmit": true,
  "rightColumn": 55,
  "topRow": 8,
  "type": "INPUT_WIDGET_V2",
  "version": 2,
  "widgetId": "l50j3psjjj",
  "widgetName": "Code_input"
}