{
  "gitSyncId": "60cd8f14165e2a21a2661090_627ea1da2c1e3f03d32990c1",
  "id": "UserOnboarding_find_user",
  "pluginId": "mysql-plugin",
  "pluginType": "DB",
  "unpublishedAction": {
    "actionConfiguration": {
      "body": "SELECT id FROM users_table where phonenumber = {{createUser_phonenumber.text}};",
      "encodeParamsToggle": true,
      "paginationType": "NONE",
      "pluginSpecifiedTemplates": [
        {
          "value": true
        }
      ],
      "timeoutInMillisecond": 10000
    },
    "confirmBeforeExecute": false,
    "datasource": {
      "id": "Untitled Datasource",
      "isAutoGenerated": false,
      "name": "Untitled Datasource",
      "pluginId": "mysql-plugin"
    },
    "dynamicBindingPathList": [],
    "executeOnLoad": false,
    "name": "find_user",
    "pageId": "UserOnboarding",
    "userSetOnLoad": true
  }
}